inventree_droplet_plugin/InvenTreeDropletPlugin.py
inventree_droplet_plugin/__init__.py
inventree_droplet_plugin-0.2.0.dist-info/METADATA
inventree_droplet_plugin-0.2.0.dist-info/WHEEL
inventree_droplet_plugin-0.2.0.dist-info/entry_points.txt
inventree_droplet_plugin-0.2.0.dist-info/top_level.txt
inventree_droplet_plugin-0.2.0.dist-info/RECORD
