Metadata-Version: 2.4
Name: inventree-droplet-plugin
Version: 0.2.0
Summary: Surface Droplet info in InvenTree
Author-email: Matthias J Mair <code@mjmair.com>
License: MIT license
Project-URL: Repository, https://github.com/invenhost/inventree-droplet-plugin
Project-URL: Bug Tracker, https://github.com/invenhost/inventree-droplet-plugin/issues
Keywords: inventree,inventree-plugin,inventree-droplet-plugin
Classifier: Programming Language :: Python :: 3
Classifier: Operating System :: OS Independent
Classifier: Development Status :: 5 - Production/Stable
Classifier: Environment :: Plugins
Classifier: Framework :: Django
Classifier: Intended Audience :: Developers
Classifier: Intended Audience :: Manufacturing
Classifier: Intended Audience :: End Users/Desktop
Classifier: Topic :: Scientific/Engineering
Classifier: License :: OSI Approved :: MIT License
Classifier: Framework :: InvenTree
Requires-Python: >=3.9
Requires-Dist: django
Provides-Extra: dev
Requires-Dist: twine; extra == "dev"
Requires-Dist: setuptools; extra == "dev"
